lab_dashboard/__init__.py
lab_dashboard/__pycache__/__init__.cpython-37.pyc
lab_dashboard/app/package-lock.json
lab_dashboard/app/package.json
lab_dashboard/app/server/common/api.js
lab_dashboard/app/server/common/api_handler.js
lab_dashboard/app/server/common/cell.js
lab_dashboard/app/server/common/experiments.js
lab_dashboard/app/server/lib/io/io.js
lab_dashboard/app/server/lib/io/node.js
lab_dashboard/app/server/lib/io/static.js
lab_dashboard/app/server/server/api_server.js
lab_dashboard/app/server/server/app.js
lab_dashboard/app/server/server/browser.js
lab_dashboard/app/server/server/consts.js
lab_dashboard/app/server/server/jupyter.js
lab_dashboard/app/server/server/lab.js
lab_dashboard/app/server/server/run_nodejs.js
lab_dashboard/app/server/server/server.js
lab_dashboard/app/server/server/tensorboard.js
lab_dashboard/app/server/server/util.js
lab_dashboard/app/server/server/experiments/cache.js
lab_dashboard/app/ui/index.html
lab_dashboard/app/ui/css/style.css
lab_dashboard/app/ui/css/style.css.map
lab_dashboard/app/ui/images/dashboard_icon.png
lab_dashboard/app/ui/images/lab_icon.png
lab_dashboard/app/ui/js/common/api.js
lab_dashboard/app/ui/js/common/api_handler.js
lab_dashboard/app/ui/js/common/cell.js
lab_dashboard/app/ui/js/common/experiments.js
lab_dashboard/app/ui/js/lib/io/ajax.js
lab_dashboard/app/ui/js/lib/io/io.js
lab_dashboard/app/ui/js/lib/weya/router.js
lab_dashboard/app/ui/js/lib/weya/weya.js
lab_dashboard/app/ui/js/ui/app.js
lab_dashboard/app/ui/js/ui/cache.js
lab_dashboard/app/ui/js/ui/codemirror.js
lab_dashboard/app/ui/js/ui/configs.js
lab_dashboard/app/ui/js/ui/diff_view.js
lab_dashboard/app/ui/js/ui/experiment_view.js
lab_dashboard/app/ui/js/ui/experiments_view.js
lab_dashboard/app/ui/js/ui/hljs.js
lab_dashboard/app/ui/js/ui/indicators.js
lab_dashboard/app/ui/js/ui/jsyaml.js
lab_dashboard/app/ui/js/ui/main.js
lab_dashboard/app/ui/js/ui/run_ui.js
lab_dashboard/app/ui/js/ui/run_view.js
lab_dashboard/app/ui/js/ui/screen.js
machine_learning_lab_dashboard-0.4.6.dist-info/METADATA
machine_learning_lab_dashboard-0.4.6.dist-info/WHEEL
machine_learning_lab_dashboard-0.4.6.dist-info/top_level.txt
machine_learning_lab_dashboard-0.4.6.dist-info/RECORD
